endaq/__init__.py
endaq/batch/__init__.py
endaq/batch/analyzer.py
endaq/batch/core.py
endaq/batch/quat.py
endaq/batch/utils/__init__.py
endaq/batch/utils/ebmlite_utils.py
endaq/batch/utils/ide_utils.py
endaq/calc/__init__.py
endaq/calc/fft.py
endaq/calc/filters.py
endaq/calc/integrate.py
endaq/calc/psd.py
endaq/calc/rotation.py
endaq/calc/shock.py
endaq/calc/stats.py
endaq/calc/utils.py
endaq/cloud/API_wrapper.py
endaq/cloud/__init__.py
endaq/cloud/core.py
endaq/cloud/scripting.py
endaq/cloud/example_scripts/__init__.py
endaq/cloud/example_scripts/correlation_explorer_dashboard.py
endaq/cloud/example_scripts/single_file_dashboard.py
endaq/ide/__init__.py
endaq/ide/files.py
endaq/ide/gdrive.py
endaq/ide/info.py
endaq/ide/measurement.py
endaq/ide/nmea.py
endaq/ide/util.py
endaq/plot/__init__.py
endaq/plot/dashboards.py
endaq/plot/plots.py
endaq/plot/t_sne.py
endaq/plot/utilities.py
endaq-1.5.3.dist-info/LICENSE
endaq-1.5.3.dist-info/METADATA
endaq-1.5.3.dist-info/WHEEL
endaq-1.5.3.dist-info/top_level.txt
endaq-1.5.3.dist-info/RECORD
