Metadata-Version: 2.1
Name: endaq
Version: 1.5.3
Summary: A comprehensive, user-centric Python API for working with enDAQ data and devices
Home-page: https://github.com/MideTechnology/endaq-python
Author: Mide Technology
Author-email: help@mide.com
License: MIT
Project-URL: Bug Tracker, https://github.com/MideTechnology/endaq-python/issues
Project-URL: Documentation, https://docs.endaq.com/en/latest/
Project-URL: Source Code, https://github.com/MideTechnology/endaq-python/tree/main
Keywords: ebml binary ide mide endaq
Classifier: Development Status :: 4 - Beta
Classifier: License :: OSI Approved :: MIT License
Classifier: Natural Language :: English
Classifier: Programming Language :: Python :: 3.8
Classifier: Programming Language :: Python :: 3.9
Classifier: Programming Language :: Python :: 3.10
Classifier: Programming Language :: Python :: 3.11
Classifier: Programming Language :: Python :: 3.12
Classifier: Topic :: Scientific/Engineering
License-File: LICENSE
Requires-Dist: backports.cached-property; python_version < "3.8"
Requires-Dist: ebmlite>=3.2.0
Requires-Dist: idelib>=3.2.8
Requires-Dist: jinja2
Requires-Dist: numpy>=1.19.5
Requires-Dist: pandas>=1.3
Requires-Dist: plotly>=5.3.1
Requires-Dist: pynmeagps
Requires-Dist: python-dotenv>=0.18.0
Requires-Dist: requests>=2.25.1
Requires-Dist: scipy>=1.7.1
Requires-Dist: pint>=0.18
Provides-Extra: test
Requires-Dist: backports.cached-property; python_version < "3.8" and extra == "test"
Requires-Dist: ebmlite>=3.2.0; extra == "test"
Requires-Dist: idelib>=3.2.8; extra == "test"
Requires-Dist: jinja2; extra == "test"
Requires-Dist: numpy>=1.19.5; extra == "test"
Requires-Dist: pandas>=1.3; extra == "test"
Requires-Dist: plotly>=5.3.1; extra == "test"
Requires-Dist: pynmeagps; extra == "test"
Requires-Dist: python-dotenv>=0.18.0; extra == "test"
Requires-Dist: requests>=2.25.1; extra == "test"
Requires-Dist: scipy>=1.7.1; extra == "test"
Requires-Dist: pint>=0.18; extra == "test"
Requires-Dist: hypothesis==6.41.0; extra == "test"
Requires-Dist: pytest; extra == "test"
Requires-Dist: pytest-cov; extra == "test"
Requires-Dist: pytest-xdist[psutil]; extra == "test"
Requires-Dist: sympy; extra == "test"
Provides-Extra: docs
Requires-Dist: backports.cached-property; python_version < "3.8" and extra == "docs"
Requires-Dist: ebmlite>=3.2.0; extra == "docs"
Requires-Dist: idelib>=3.2.8; extra == "docs"
Requires-Dist: jinja2; extra == "docs"
Requires-Dist: numpy>=1.19.5; extra == "docs"
Requires-Dist: pandas>=1.3; extra == "docs"
Requires-Dist: plotly>=5.3.1; extra == "docs"
Requires-Dist: pynmeagps; extra == "docs"
Requires-Dist: python-dotenv>=0.18.0; extra == "docs"
Requires-Dist: requests>=2.25.1; extra == "docs"
Requires-Dist: scipy>=1.7.1; extra == "docs"
Requires-Dist: pint>=0.18; extra == "docs"
Requires-Dist: sphinx; extra == "docs"
Requires-Dist: pydata-sphinx-theme; extra == "docs"
Requires-Dist: sphinx-plotly-directive; extra == "docs"
Requires-Dist: sphinxcontrib-spelling; extra == "docs"
Requires-Dist: nbsphinx; extra == "docs"
Provides-Extra: example
Requires-Dist: backports.cached-property; python_version < "3.8" and extra == "example"
Requires-Dist: ebmlite>=3.2.0; extra == "example"
Requires-Dist: idelib>=3.2.8; extra == "example"
Requires-Dist: jinja2; extra == "example"
Requires-Dist: numpy>=1.19.5; extra == "example"
Requires-Dist: pandas>=1.3; extra == "example"
Requires-Dist: plotly>=5.3.1; extra == "example"
Requires-Dist: pynmeagps; extra == "example"
Requires-Dist: python-dotenv>=0.18.0; extra == "example"
Requires-Dist: requests>=2.25.1; extra == "example"
Requires-Dist: scipy>=1.7.1; extra == "example"
Requires-Dist: pint>=0.18; extra == "example"
